mindcontrol_types/__init__.py
mindcontrol_types/anthropic.py
mindcontrol_types/collection.py
mindcontrol_types/dependency.py
mindcontrol_types/fragment.py
mindcontrol_types/llm.py
mindcontrol_types/log.py
mindcontrol_types/openai.py
mindcontrol_types/package.py
mindcontrol_types/payload.py
mindcontrol_types/perplexity.py
mindcontrol_types/prompt.py
mindcontrol_types/py.typed
mindcontrol_types/resource.py
mindcontrol_types/signature.py
mindcontrol_types/template.py
mindcontrol_types/var.py
mindcontrol_types/version.py
mindcontrol_types/webhook.py
mindcontrol_types-0.21.0.dist-info/METADATA
mindcontrol_types-0.21.0.dist-info/WHEEL
mindcontrol_types-0.21.0.dist-info/RECORD
