Metadata-Version: 2.3
Name: mindcontrol-types
Version: 0.21.0
Summary: Mind Control types
License: BSD-3-Clause
Author: Sasha Koss
Author-email: koss@nocorp.me
Requires-Python: >=3.8,<4.0
Classifier: License :: OSI Approved :: BSD License
Classifier: Programming Language :: Python :: 3
Classifier: Programming Language :: Python :: 3.8
Classifier: Programming Language :: Python :: 3.9
Classifier: Programming Language :: Python :: 3.10
Classifier: Programming Language :: Python :: 3.11
Classifier: Programming Language :: Python :: 3.12
Classifier: Programming Language :: Python :: 3.13
Requires-Dist: genotype-json-types (==0.3.0)
Requires-Dist: genotype-runtime (>=0.4,<0.5)
Requires-Dist: pydantic (>=2.9,<3.0)
Requires-Dist: typing-extensions (>=4,<5)
